[
    {
        "kennelId": 1,
        "description": "Comfortable and secure kennel for your pet.",
        "capacity": 20,
        "dailyCost": 25.00
    },
    {
        "kennelId": 2,
        "description": "Luxury kennel with premium amenities.",
        "capacity": 10,
        "dailyCost": 40.00
    },
    {
        "kennelId": 3,
        "description": "Budget-friendly kennel for short-term stays.",
        "capacity": 30,
        "dailyCost": 15.00
    },
    {
        "kennelId": 4,
        "description": "Large kennel with outdoor play area.",
        "capacity": 25,
        "dailyCost": 30.00
    },
    {
        "kennelId": 5,
        "description": "Climate-controlled kennel for exotic pets.",
        "capacity": 15,
        "dailyCost": 35.00
    }
]